crawtext/url.pyc
crawtext/encoding.pyc
crawtext/report.pyc
crawtext/query.py
crawtext/utils.py
crawtext/urls.pyc
crawtext/urls.py
crawtext/filter.pyc
crawtext/__init__.py
crawtext/export.pyc
crawtext/filter.py
crawtext/encoding.py
crawtext/crawtext.py
crawtext/url.py
crawtext/crawler.py
crawtext/text.py
crawtext/runner
crawtext/crawler.pyc
crawtext/report.py
crawtext/query.pyc
crawtext/export.py
crawtext/ressources/useragents.txt
crawtext/ressources/google_sources.txt
crawtext/ressources/easylist.txt
crawtext/ressources/popular_urls.txt
crawtext/ressources/template.html
crawtext/ressources/ask_yes_no.py
crawtext/ressources/stopwords_en2.txt
crawtext/ressources/stopwords_en.txt
crawtext/ressources/popular_sources.txt
crawtext/packages/__init__.pyc
crawtext/packages/emails.py
crawtext/packages/__init__.py
crawtext/packages/private.pyc
crawtext/packages/format_email.pyc
crawtext/packages/format_email.py
crawtext/projects/RRI/results_19-11-14_13:20.csv
crawtext/projects/RRI/sources_19-11-14_13:19.csv
crawtext/projects/RRI/sources_19-11-14_13:07.json
crawtext/projects/RRI/logs_19-11-14_13:38.csv
crawtext/projects/RRI/logs_20-11-14_10:04.json
crawtext/projects/RRI/sources_19-11-14_13:12.json
crawtext/projects/RRI/logs_19-11-14_13:22.csv
crawtext/projects/RRI/results_19-11-14_13:12.json
crawtext/projects/RRI/results_19-11-14_13:38.csv
crawtext/projects/RRI/results_19-11-14_13:11.json
crawtext/projects/RRI/sources_20-11-14_10:08.csv
crawtext/projects/RRI/logs_19-11-14_13:15.csv
crawtext/projects/RRI/logs_19-11-14_13:19.csv
crawtext/projects/RRI/results_19-11-14_13:19.csv
crawtext/projects/RRI/sources_19-11-14_13:38.csv
crawtext/projects/RRI/logs_19-11-14_13:13.json
crawtext/projects/RRI/logs_19-11-14_13:17.csv
crawtext/projects/RRI/results_19-11-14_13:18.csv
crawtext/projects/RRI/logs_19-11-14_13:11.json
crawtext/projects/RRI/sources_19-11-14_13:22.csv
crawtext/projects/RRI/results_19-11-14_13:17.csv
crawtext-4.1.1.dist-info/entry_points.txt
crawtext-4.1.1.dist-info/METADATA
crawtext-4.1.1.dist-info/metadata.json
crawtext-4.1.1.dist-info/top_level.txt
crawtext-4.1.1.dist-info/dependency_links.txt
crawtext-4.1.1.dist-info/DESCRIPTION.rst
crawtext-4.1.1.dist-info/RECORD
crawtext-4.1.1.dist-info/WHEEL
