Metadata-Version: 2.0
Name: crawtext
Version: 4.1.1
Summary: Tiny WebCrawler in CLI
Home-page: https://github.com/cortext/crawtext
Author: Constance de Quatrebarbes
Author-email: 4barbes@gmail.com
License: MIT
Keywords: web crawler,web scrapping
Platform: UNKNOWN
Classifier: Development Status :: 4 - Beta
Classifier: Environment :: Other Environment
Classifier: Intended Audience :: Developers
Classifier: License :: OSI Approved :: Apache Software License
Classifier: Operating System :: MacOS :: MacOS X
Classifier: Operating System :: POSIX
Classifier: Programming Language :: Python
Classifier: Programming Language :: Python
Classifier: Programming Language :: Python :: 2
Classifier: Programming Language :: Python :: 2.6
Classifier: Programming Language :: Python :: 2.7
Classifier: Topic :: Internet
Classifier: Topic :: Utilities
Classifier: Topic :: Software Development :: Libraries :: Python Modules
Requires-Dist: Pillow
Requires-Dist: lxml
Requires-Dist: cssselect
Requires-Dist: jieba
Requires-Dist: beautifulsoup
Requires-Dist: nltk
Requires-Dist: six
Requires-Dist: pymongo
Requires-Dist: argparse
Requires-Dist: docopt
Requires-Dist: tld
Requires-Dist: wsgiref
Requires-Dist: PyYAML
Requires-Dist: MarkupSafe
Requires-Dist: JINJA2
